setup.py
bibtex_lexer/__init__.py
bibtex_pygments_lexer.egg-info/PKG-INFO
bibtex_pygments_lexer.egg-info/SOURCES.txt
bibtex_pygments_lexer.egg-info/dependency_links.txt
bibtex_pygments_lexer.egg-info/entry_points.txt
bibtex_pygments_lexer.egg-info/top_level.txt