Metadata-Version: 1.0
Name: bibtex-pygments-lexer
Version: 0.0.1
Summary: Pygments Lexer for BibTeX
Home-page: UNKNOWN
Author: Marco D. Adelfio
Author-email: UNKNOWN
License: UNKNOWN
Platform: UNKNOWN
